<annotation>
	<folder>526-1050 zehra</folder>
	<filename>20220923_195728.jpg</filename>
	<path>C:\Users\HAKKI\Desktop\526-1050 zehra\20220923_195728.jpg</path>
	<source>
		<database>Unknown</database>
	</source>
	<size>
		<width>3000</width>
		<height>4000</height>
		<depth>3</depth>
	</size>
	<segmented>0</segmented>
	<object>
		<name>hoop</name>
		<pose>Unspecified</pose>
		<truncated>0</truncated>
		<difficult>0</difficult>
		<bndbox>
			<xmin>1278</xmin>
			<ymin>875</ymin>
			<xmax>2297</xmax>
			<ymax>1100</ymax>
		</bndbox>
	</object>
</annotation>
