<annotation>
	<folder>train</folder>
	<filename>IMG_20220216_122030.jpg</filename>
	<path>data/train/IMG_20220216_122030.jpg</path>
	<source>
		<database>Unknown</database>
	</source>
	<size>
		<width>3000</width>
		<height>4000</height>
		<depth>3</depth>
	</size>
	<segmented>0</segmented>
	<object>
		<name>hoop</name>
		<pose>Unspecified</pose>
		<truncated>0</truncated>
		<difficult>0</difficult>
		<bndbox>
			<xmin>1056</xmin>
			<ymin>1305</ymin>
			<xmax>1943</xmax>
			<ymax>1467</ymax>
		</bndbox>
	</object>
</annotation>
